jarpcdantic/__init__.py
jarpcdantic/client.py
jarpcdantic/context.py
jarpcdantic/dispatcher.py
jarpcdantic/errors.py
jarpcdantic/format.py
jarpcdantic/manager.py
jarpcdantic/router.py
jarpcdantic/utils.py
jarpcdantic-0.1.18.dist-info/LICENSE
jarpcdantic-0.1.18.dist-info/METADATA
jarpcdantic-0.1.18.dist-info/WHEEL
jarpcdantic-0.1.18.dist-info/top_level.txt
jarpcdantic-0.1.18.dist-info/RECORD
