Metadata-Version: 2.2
Name: jarpcdantic
Version: 0.1.18
Summary: JSON Advanced RPC with Pydantic
Home-page: https://github.com/whiteapfel/jarpcdantic/
Download-URL: https://pypi.org/project/jarpcdantic/
Maintainer: WhiteApfel
Maintainer-email: white@pfel.ru
License: Mozilla Public License 2.0
Classifier: Development Status :: 3 - Alpha
Classifier: Programming Language :: Python :: 3.12
Classifier: Intended Audience :: Developers
Classifier: License :: OSI Approved :: Mozilla Public License 2.0 (MPL 2.0)
Classifier: Topic :: Utilities
Requires: pydantic
License-File: LICENSE
Dynamic: classifier
Dynamic: description
Dynamic: description-content-type
Dynamic: download-url
Dynamic: home-page
Dynamic: license
Dynamic: maintainer
Dynamic: maintainer-email
Dynamic: requires
Dynamic: summary
